{"anchor_name": "libaom_20191019_bbe0a0a", "anchor_codec": "libaom", "test_name": "svtav1_20191025_cc303a3", "test_codec": "svtav1", "sequences": {"Cosmos1_1920x856_BT2100_PQ_24fps": {"CPSNRY": 4.657, "CPSNRU": -1.737, "CPSNRV": 19.868, "CPSNRYUV": 5.26, "TPSNRY": 3.789, "TPSNRU": -2.213, "TPSNRV": 19.39, "TPSNRYUV": 3.678, "BDVMAF": 1.793, "EncTimeInc": -83.31}, "DOTA2_60f_420": {"CPSNRY": 1.176, "CPSNRU": -6.371, "CPSNRV": -5.264, "CPSNRYUV": -0.511, "TPSNRY": 1.796, "TPSNRU": -5.652, "TPSNRV": -4.656, "TPSNRYUV": 0.752, "BDVMAF": 2.263, "EncTimeInc": -41.656}, "KristenAndSara_1280x720_60f": {"CPSNRY": 4.356, "CPSNRU": 0.92, "CPSNRV": -0.797, "CPSNRYUV": 3.41, "TPSNRY": 4.608, "TPSNRU": 0.936, "TPSNRV": -0.803, "TPSNRYUV": 4.132, "BDVMAF": 7.392, "EncTimeInc": -28.817}, "MINECRAFT_60f_420": {"CPSNRY": 9.681, "CPSNRU": 18.201, "CPSNRV": 9.047, "CPSNRYUV": 10.485, "TPSNRY": 9.534, "TPSNRU": 18.463, "TPSNRV": 8.777, "TPSNRYUV": 9.666, "BDVMAF": 6.664, "EncTimeInc": -77.671}, "Market3_1920x1080p_50_10b_pq_709": {"CPSNRY": 4.538, "CPSNRU": -11.812, "CPSNRV": -12.309, "CPSNRYUV": 1.448, "TPSNRY": 4.832, "TPSNRU": -12.005, "TPSNRV": -12.564, "TPSNRYUV": 3.975, "BDVMAF": 9.596, "EncTimeInc": -73.305}, "Netflix_Aerial_1920x1080_60fps_8": {"CPSNRY": 5.079, "CPSNRU": -7.616, "CPSNRV": -7.61, "CPSNRYUV": 3.045, "TPSNRY": 5.247, "TPSNRU": -7.834, "TPSNRV": -7.858, "TPSNRYUV": 3.972, "BDVMAF": 3.096, "EncTimeInc": -65.52}, "Netflix_Boat_1920x1080_60fps_8bi": {"CPSNRY": 3.815, "CPSNRU": -7.93, "CPSNRV": -13.008, "CPSNRYUV": 1.096, "TPSNRY": 4.718, "TPSNRU": -7.569, "TPSNRV": -12.935, "TPSNRYUV": 3.082, "BDVMAF": 3.308, "EncTimeInc": -71.347}, "Netflix_Crosswalk_1920x1080_60fp": {"CPSNRY": 7.95, "CPSNRU": 1.274, "CPSNRV": -0.247, "CPSNRYUV": 6.608, "TPSNRY": 8.092, "TPSNRU": 1.621, "TPSNRV": 0.135, "TPSNRYUV": 7.368, "BDVMAF": 7.98, "EncTimeInc": -47.424}, "Netflix_DrivingPOV_1280x720_60fp": {"CPSNRY": 3.91, "CPSNRU": -0.364, "CPSNRV": -0.383, "CPSNRYUV": 3.126, "TPSNRY": 4.484, "TPSNRU": -0.405, "TPSNRV": -0.366, "TPSNRYUV": 3.871, "BDVMAF": 7.391, "EncTimeInc": -60.87}, "Netflix_FoodMarket_1920x1080_60f": {"CPSNRY": 6.204, "CPSNRU": -6.665, "CPSNRV": -4.597, "CPSNRYUV": 4.062, "TPSNRY": 6.883, "TPSNRU": -6.338, "TPSNRV": -4.619, "TPSNRYUV": 5.655, "BDVMAF": 5.584, "EncTimeInc": -69.832}, "Netflix_PierSeaside_1920x1080_60": {"CPSNRY": 0.639, "CPSNRU": -10.127, "CPSNRV": -9.934, "CPSNRYUV": -1.35, "TPSNRY": 1.69, "TPSNRU": -9.955, "TPSNRV": -9.691, "TPSNRYUV": -0.226, "BDVMAF": 1.212, "EncTimeInc": -51.588}, "Netflix_RollerCoaster_1280x720_6": {"CPSNRY": 6.505, "CPSNRU": -3.204, "CPSNRV": -6.406, "CPSNRYUV": 4.169, "TPSNRY": 6.973, "TPSNRU": -3.074, "TPSNRV": -6.351, "TPSNRYUV": 4.994, "BDVMAF": 5.021, "EncTimeInc": -45.907}, "Netflix_SquareAndTimelapse_1920x": {"CPSNRY": 4.964, "CPSNRU": -5.746, "CPSNRV": -4.71, "CPSNRYUV": 2.766, "TPSNRY": 5.531, "TPSNRU": -5.716, "TPSNRV": -4.622, "TPSNRYUV": 4.233, "BDVMAF": 3.261, "EncTimeInc": -14.642}, "Netflix_TunnelFlag_1920x1080_60f": {"CPSNRY": 7.367, "CPSNRU": -12.643, "CPSNRV": -4.429, "CPSNRYUV": 4.005, "TPSNRY": 8.368, "TPSNRU": -12.435, "TPSNRV": -4.274, "TPSNRYUV": 6.715, "BDVMAF": 22.952, "EncTimeInc": -53.242}, "STARCRAFT_60f_420": {"CPSNRY": 2.786, "CPSNRU": -1.903, "CPSNRV": -0.082, "CPSNRYUV": 2.014, "TPSNRY": 2.924, "TPSNRU": -1.763, "TPSNRV": -0.008, "TPSNRYUV": 2.501, "BDVMAF": 4.719, "EncTimeInc": 22.611}, "ShowGirl2TeaserClip4000_1920x108": {"CPSNRY": 3.029, "CPSNRU": -13.297, "CPSNRV": -16.834, "CPSNRYUV": -1.096, "TPSNRY": 3.02, "TPSNRU": -13.353, "TPSNRV": -16.878, "TPSNRYUV": 1.294, "BDVMAF": 8.178, "EncTimeInc": -73.048}, "Starting_1920x1080p_50_10b_pq_70": {"CPSNRY": 1.911, "CPSNRU": -6.714, "CPSNRV": -4.144, "CPSNRYUV": 0.507, "TPSNRY": 2.085, "TPSNRU": -6.776, "TPSNRV": -4.173, "TPSNRYUV": 1.217, "BDVMAF": 10.576, "EncTimeInc": -59.068}, "aspen_1080p_60f": {"CPSNRY": 19.589, "CPSNRU": 5.187, "CPSNRV": -5.849, "CPSNRYUV": 14.621, "TPSNRY": 20.176, "TPSNRU": 5.327, "TPSNRV": -5.844, "TPSNRYUV": 17.741, "BDVMAF": 20.822, "EncTimeInc": -46.654}, "blue_sky_360p_60f": {"CPSNRY": 8.495, "CPSNRU": 1.603, "CPSNRV": -1.397, "CPSNRYUV": 6.715, "TPSNRY": 9.248, "TPSNRU": 1.838, "TPSNRV": -1.149, "TPSNRYUV": 7.613, "BDVMAF": 5.856, "EncTimeInc": -17.419}, "dark720p_60f": {"CPSNRY": 12.82, "CPSNRU": 16.595, "CPSNRV": 15.405, "CPSNRYUV": 13.38, "TPSNRY": 17.548, "TPSNRU": 21.286, "TPSNRV": 20.467, "TPSNRYUV": 19.33, "BDVMAF": 27.208, "EncTimeInc": -45.426}, "ducks_take_off_1080p50_60f": {"CPSNRY": 3.914, "CPSNRU": 5.591, "CPSNRV": 15.202, "CPSNRYUV": 4.894, "TPSNRY": 2.328, "TPSNRU": 5.057, "TPSNRV": 15.443, "TPSNRYUV": 2.841, "BDVMAF": 1.039, "EncTimeInc": -77.245}, "gipsrestat720p_60f": {"CPSNRY": 2.408, "CPSNRU": 5.021, "CPSNRV": 5.865, "CPSNRYUV": 2.988, "TPSNRY": 2.295, "TPSNRU": 4.865, "TPSNRV": 5.771, "TPSNRYUV": 2.664, "BDVMAF": 1.712, "EncTimeInc": -37.673}, "kirland360p_60f": {"CPSNRY": -1.074, "CPSNRU": 0.624, "CPSNRV": 1.95, "CPSNRYUV": -0.716, "TPSNRY": -1.071, "TPSNRU": -1.397, "TPSNRV": 1.884, "TPSNRYUV": -0.871, "BDVMAF": -0.924, "EncTimeInc": 16.134}, "life_1080p30_60f": {"CPSNRY": 3.883, "CPSNRU": -5.421, "CPSNRV": -6.323, "CPSNRYUV": 1.649, "TPSNRY": 4.275, "TPSNRU": -4.989, "TPSNRV": -6.03, "TPSNRYUV": 3.296, "BDVMAF": 4.486, "EncTimeInc": -6.377}, "niklas360p_60f": {"CPSNRY": 6.821, "CPSNRU": 11.557, "CPSNRV": 9.161, "CPSNRYUV": 7.509, "TPSNRY": 7.198, "TPSNRU": 11.641, "TPSNRV": 9.436, "TPSNRYUV": 7.348, "BDVMAF": 5.093, "EncTimeInc": -28.263}, "red_kayak_360p_60f": {"CPSNRY": 0.475, "CPSNRU": 9.006, "CPSNRV": 85.431, "CPSNRYUV": 4.353, "TPSNRY": -1.347, "TPSNRU": 8.466, "TPSNRV": 83.086, "TPSNRYUV": -1.064, "BDVMAF": -3.259, "EncTimeInc": -60.734}, "rush_hour_1080p25_60f": {"CPSNRY": 8.368, "CPSNRU": -2.281, "CPSNRV": -0.784, "CPSNRYUV": 6.162, "TPSNRY": 8.566, "TPSNRU": -2.043, "TPSNRV": -0.471, "TPSNRYUV": 7.353, "BDVMAF": 7.276, "EncTimeInc": -47.428}, "shields_640x360_60f": {"CPSNRY": 1.226, "CPSNRU": 0.21, "CPSNRV": -1.166, "CPSNRYUV": 0.77, "TPSNRY": 1.47, "TPSNRU": 0.211, "TPSNRV": 1.202, "TPSNRYUV": 1.213, "BDVMAF": 1.473, "EncTimeInc": -11.499}, "speed_bag_640x360_60f": {"CPSNRY": 4.65, "CPSNRU": 4.611, "CPSNRV": 5.109, "CPSNRYUV": 4.688, "TPSNRY": 3.57, "TPSNRU": 3.745, "TPSNRV": 4.21, "TPSNRYUV": 3.559, "BDVMAF": 3.771, "EncTimeInc": 36.392}, "thaloundeskmtg360p_60f": {"CPSNRY": 3.218, "CPSNRU": 3.206, "CPSNRV": 4.04, "CPSNRYUV": 3.312, "TPSNRY": 1.34, "TPSNRU": 2.19, "TPSNRV": 3.488, "TPSNRYUV": 1.44, "BDVMAF": 5.138, "EncTimeInc": 44.739}, "touchdown_pass_1080p_60f": {"CPSNRY": 7.02, "CPSNRU": -15.457, "CPSNRV": -14.332, "CPSNRYUV": 2.6, "TPSNRY": 6.833, "TPSNRU": -15.604, "TPSNRV": -14.279, "TPSNRYUV": 5.782, "BDVMAF": 1.817, "EncTimeInc": -63.057}, "vidyo1_720p_60fps_60f": {"CPSNRY": 6.471, "CPSNRU": -4.063, "CPSNRV": -1.968, "CPSNRYUV": 4.775, "TPSNRY": 6.531, "TPSNRU": -4.092, "TPSNRV": -1.987, "TPSNRYUV": 5.55, "BDVMAF": 7.029, "EncTimeInc": -28.88}, "vidyo4_720p_60fps_60f": {"CPSNRY": 4.354, "CPSNRU": -3.517, "CPSNRV": -2.944, "CPSNRYUV": 2.806, "TPSNRY": 4.725, "TPSNRU": -3.376, "TPSNRV": -2.894, "TPSNRYUV": 4.134, "BDVMAF": 3.931, "EncTimeInc": -50.065}, "wikipedia_420": {"CPSNRY": -16.962, "CPSNRU": -10.609, "CPSNRV": -11.83, "CPSNRYUV": -15.972, "TPSNRY": -17.067, "TPSNRU": -10.791, "TPSNRV": -11.933, "TPSNRYUV": -16.136, "BDVMAF": -4.453, "EncTimeInc": -14.854}}, "averages": {"Test": {"svtav1_20191025_cc303a3": {"CPSNRY": 4.537, "CPSNRU": -1.584, "CPSNRV": 0.992, "CPSNRYUV": 3.341, "TPSNRY": 4.741, "TPSNRU": -1.522, "TPSNRV": 1.144, "TPSNRYUV": 4.079, "BDVMAF": 5.853, "EncTimeInc": -39.204}}, "EncWidth": {"640": {"CPSNRY": 3.402, "CPSNRU": 4.403, "CPSNRV": 14.732, "CPSNRYUV": 3.805, "TPSNRY": 2.916, "TPSNRU": 3.814, "TPSNRV": 14.594, "TPSNRYUV": 2.748, "BDVMAF": 2.45, "EncTimeInc": -2.95}, "1280": {"CPSNRY": 5.832, "CPSNRU": 1.627, "CPSNRV": 1.253, "CPSNRYUV": 4.951, "TPSNRY": 6.738, "TPSNRU": 2.306, "TPSNRV": 1.977, "TPSNRYUV": 6.382, "BDVMAF": 8.526, "EncTimeInc": -42.52}, "1920": {"CPSNRY": 4.48, "CPSNRU": -4.804, "CPSNRV": -3.908, "CPSNRYUV": 2.615, "TPSNRY": 4.681, "TPSNRU": -4.728, "TPSNRV": -3.854, "TPSNRYUV": 3.738, "BDVMAF": 6.108, "EncTimeInc": -50.733}}, "FPS": {"24.0": {"CPSNRY": 4.657, "CPSNRU": -1.737, "CPSNRV": 19.868, "CPSNRYUV": 5.26, "TPSNRY": 3.789, "TPSNRU": -2.213, "TPSNRV": 19.39, "TPSNRYUV": 3.678, "BDVMAF": 1.793, "EncTimeInc": -83.31}, "25.0": {"CPSNRY": 6.631, "CPSNRU": -4.658, "CPSNRV": -6.338, "CPSNRYUV": 3.927, "TPSNRY": 6.945, "TPSNRU": -4.519, "TPSNRV": -6.166, "TPSNRYUV": 5.42, "BDVMAF": 7.103, "EncTimeInc": -45.965}, "29.97": {"CPSNRY": 7.933, "CPSNRU": 0.836, "CPSNRV": 17.59, "CPSNRYUV": 6.565, "TPSNRY": 7.308, "TPSNRU": 0.484, "TPSNRV": 16.793, "TPSNRYUV": 6.504, "BDVMAF": 5.788, "EncTimeInc": -33.513}, "30.0": {"CPSNRY": 1.451, "CPSNRU": 2.659, "CPSNRV": 2.067, "CPSNRYUV": 1.527, "TPSNRY": 2.037, "TPSNRU": 2.99, "TPSNRV": 2.885, "TPSNRYUV": 2.401, "BDVMAF": 6.091, "EncTimeInc": -5.674}, "50.0": {"CPSNRY": 2.799, "CPSNRU": -1.541, "CPSNRV": 0.69, "CPSNRYUV": 2.122, "TPSNRY": 2.602, "TPSNRU": -1.729, "TPSNRV": 1.136, "TPSNRYUV": 2.382, "BDVMAF": 4.879, "EncTimeInc": -51.758}, "60.0": {"CPSNRY": 5.017, "CPSNRU": -3.317, "CPSNRV": -3.555, "CPSNRYUV": 3.367, "TPSNRY": 5.474, "TPSNRU": -3.146, "TPSNRV": -3.477, "TPSNRYUV": 4.427, "BDVMAF": 6.12, "EncTimeInc": -45.657}}, "Bitdepth": {"8": {"CPSNRY": 4.67, "CPSNRU": -0.677, "CPSNRV": 1.572, "CPSNRYUV": 3.582, "TPSNRY": 4.916, "TPSNRU": -0.58, "TPSNRV": 1.771, "TPSNRYUV": 4.284, "BDVMAF": 5.629, "EncTimeInc": -34.807}, "10": {"CPSNRY": 3.534, "CPSNRU": -8.39, "CPSNRV": -3.355, "CPSNRYUV": 1.53, "TPSNRY": 3.431, "TPSNRU": -8.587, "TPSNRV": -3.556, "TPSNRYUV": 2.541, "BDVMAF": 7.536, "EncTimeInc": -72.183}}}}